scriptures/__init__.py
scriptures/reference.py
scriptures/text.py
scriptures/canons/__init__.py
scriptures/canons/base.py
scriptures/canons/catholic.py
scriptures/canons/deuterocanon.py
scriptures/canons/kjv1611.py
scriptures/canons/protestant.py
scriptures/tests/__init__.py
scriptures/tests/test_1611_booknames.py
scriptures/tests/test_deuterocanon_booknames.py
scriptures/tests/test_normalization.py
scriptures/tests/test_protestant_booknames.py
scriptures/tests/test_ref_extraction_from_text.py
scriptures/tests/test_ref_to_string.py
beatitud_scriptures-4.0.0.dist-info/LICENSE
beatitud_scriptures-4.0.0.dist-info/METADATA
beatitud_scriptures-4.0.0.dist-info/WHEEL
beatitud_scriptures-4.0.0.dist-info/top_level.txt
beatitud_scriptures-4.0.0.dist-info/RECORD
