Metadata-Version: 2.1
Name: beatitud-scriptures
Version: 4.0.0
Summary: bible-ref-py is a python library built on top of python-scriptures library, implemented by David Davis <davisd@davisd.com> (Copyright (c) 2010-2015). It is a Python package and regular expression library for validating, extracting, and normalizing biblical references from text.
Home-page: https://github.com/beatitud/bible-ref-py/
Author: Antoine Rose
Author-email: antoine_rose@hotmail.fr
License: MIT
Keywords: bible,ref,parser,catholic,protestant
Platform: UNKNOWN
